sensirion_driver_adapters/__init__.py
sensirion_driver_adapters/channel.py
sensirion_driver_adapters/channel_provider.py
sensirion_driver_adapters/multi_channel.py
sensirion_driver_adapters/multi_device_support.py
sensirion_driver_adapters/multi_sensor_bridge.py
sensirion_driver_adapters/rx_tx_data.py
sensirion_driver_adapters/transfer.py
sensirion_driver_adapters/version.py
sensirion_driver_adapters/i2c_adapter/__init__.py
sensirion_driver_adapters/i2c_adapter/i2c_channel.py
sensirion_driver_adapters/i2c_adapter/linux_i2c_channel_provider.py
sensirion_driver_adapters/i2c_adapter/sensor_bridge_i2c_channel_provider.py
sensirion_driver_adapters/mocks/__init__.py
sensirion_driver_adapters/mocks/i2c_connection_mock.py
sensirion_driver_adapters/mocks/i2c_sensor_mock.py
sensirion_driver_adapters/mocks/mock_i2c_channel_provider.py
sensirion_driver_adapters/mocks/mock_shdlc_channel_provider.py
sensirion_driver_adapters/mocks/response_provider.py
sensirion_driver_adapters/mocks/shdlc_sensor_mock.py
sensirion_driver_adapters/mocks/shdlc_transceiver_mock.py
sensirion_driver_adapters/shdlc_adapter/__init__.py
sensirion_driver_adapters/shdlc_adapter/shdlc_channel.py
sensirion_driver_adapters/shdlc_adapter/shdlc_serial_channel_provider.py
sensirion_driver_adapters-2.3.1.dist-info/LICENSE
sensirion_driver_adapters-2.3.1.dist-info/METADATA
sensirion_driver_adapters-2.3.1.dist-info/WHEEL
sensirion_driver_adapters-2.3.1.dist-info/top_level.txt
sensirion_driver_adapters-2.3.1.dist-info/RECORD
