Metadata-Version: 2.1
Name: sensirion-driver-adapters
Version: 2.3.1
Summary: Adapter classes to use sensirion_i2c_driver package
Home-page: http://developers.sensirion.com
Author: Rolf Laich
Author-email: rolf.laich@sensirion.com
License: BSD 3-Clause License
Keywords: driver driver-generator
Platform: UNKNOWN
Classifier: Intended Audience :: Developers
Classifier: License :: Other/Proprietary License
Classifier: Programming Language :: Python :: 3.6
Classifier: Programming Language :: Python :: 3.7
Classifier: Programming Language :: Python :: 3.8
Classifier: Programming Language :: Python :: 3.11
Classifier: Topic :: Software Development :: Libraries :: Python Modules
Requires-Python: >=3.6, <4
Requires-Dist: sensirion-i2c-driver
Requires-Dist: sensirion-shdlc-driver
Requires-Dist: sensirion-shdlc-sensorbridge
Provides-Extra: docs
Requires-Dist: lazy-object-proxy (~=1.7.1) ; extra == 'docs'
Requires-Dist: sphinx (~=7.1.0) ; extra == 'docs'
Requires-Dist: docutils (~=0.18.0) ; extra == 'docs'
Requires-Dist: sphinx-rtd-theme (~=1.3.0) ; extra == 'docs'
Requires-Dist: sphinx-autoapi (~=3.0.0) ; extra == 'docs'
Provides-Extra: test
Requires-Dist: flake8 (~=6.0.0) ; extra == 'test'
Requires-Dist: pytest (~=8.1.1) ; extra == 'test'
Requires-Dist: pytest-cov (~=5.0.0) ; extra == 'test'
